{
    "SaveName": "",
    "GameMode": "",
    "Gravity": 0.5,
    "PlayArea": 0.5,
    "Date": "",
    "Table": "",
    "Sky": "",
    "Note": "",
    "Rules": "",
    "XmlUI": "",
    "CustomUIAssets": null,
    "LuaScript": "",
    "LuaScriptState": "",
    "ObjectStates": [
      {
        "Name": "PiecePack_Suns",
        "Transform": {
          "posX": 0.0,
          "posY": 0.0,
          "posZ": 0.0,
          "rotX": 0.0,
          "rotY": 0.0,
          "rotZ": 0.0,
          "scaleX": 0.25,
          "scaleY": 0.25,
          "scaleZ": 0.25
        },
        "Nickname": "Deck Generator Tool",
        "Description": "This tool uses a script to name and give descriptions to cards. Generated with wstools.",
        "ColorDiffuse": {
          "r": 0.0,
          "g": 0.0,
          "b": 0.0
        },
        "Locked": false,
        "Grid": true,
        "Snap": true,
        "Autoraise": true,
        "Sticky": true,
        "Tooltip": true,
        "GridProjection": false,
        "HideWhenFaceDown": false,
        "Hands": false,
        "AltSound": null,
        "MaterialIndex": null,
        "MeshIndex": 6,
        "Layer": null,
        "Number": null,
        "CardID": null,
        "SidewaysCard": null,
        "RPGmode": null,
        "RPGdead": null,
        "FogColor": null,
        "FogHidePointers": null,
        "FogReverseHiding": null,
        "FogSeethrough": null,
        "DeckIDs": null,
        "CustomDeck": null,
        "CustomMesh": null,
        "CustomImage": null,
        "CustomAssetbundle": null,
        "FogOfWar": null,
        "FogOfWarRevealer": null,
        "Clock": null,
        "Counter": null,
        "Tablet": null,
        "Mp3Player": null,
        "Calculator": null,
        "Text": null,
        "XmlUI": "<Defaults>\r\n    <Panel class=\"Window\" width=\"400\" height=\"175\" color=\"#FFFFFF40\" outline=\"#404040\" />\r\n    <Panel class=\"TopBar\" height=\"30\" rectAlignment=\"UpperCenter\" color=\"#191970\" />\r\n    <Text class=\"WindowTitle\" fontSize=\"18\" height=\"20\" fontStyle=\"Bold\" rectAlignment=\"UpperCenter\" color=\"#FFFFFF\" />\r\n    <Button class=\"topButtons\" width=\"20\" height=\"20\" rectAlignment=\"UpperRight\" color=\"#eeeeee\" />\r\n</Defaults>\r\n\r\n<Panel class=\"Window\" id=\"deckGeneratorWindow\" allowDragging=\"True\" returnToOriginalPositionWhenReleased=\"false\" rectAlignment=\"MiddleRight\">\r\n    <Panel class=\"TopBar\" id=\"TopBar\">\r\n        <Text class=\"WindowTitle\" offsetXY=\"0 -5\">Generate Deck</Text>\r\n        <!--\r\n        <Button id=\"minimizeButton\"\r\n            class=\"topButtons\"\r\n            textColor=\"#000000\"\r\n            text=\"_\"\r\n            offsetXY=\"-25 -5\"\r\n            onClick=\"minimize\"/>\r\n        -->\r\n        <Button id=\"closeButton\"\r\n                class=\"topButtons\"\r\n                color=\"#990000\"\r\n                textColor=\"#FFFFFF\"\r\n                text=\"X\"\r\n                offsetXY=\"-5 -5\"\r\n                onClick=\"close\" />\r\n    </Panel>\r\n    <InputField id=\"deckImageText\"\r\n                onValueChanged=\"setDeckImage\"\r\n                offsetXY=\"180 5\"\r\n                preferredWidth=\"250\"\r\n                rectAlignment=\"MiddleRight\"\r\n                placeholder=\"Paste Image Here...\">\r\n    </InputField>\r\n    <InputField id=\"charaSleevesText\"\r\n                onValueChanged=\"setCharacterSleeves\"\r\n                offsetXY=\"180 -30\"\r\n                preferredWidth=\"250\"\r\n                rectAlignment=\"MiddleRight\"\r\n                placeholder=\"https://i.imgur.com/fRYj5tS.jpg\">\r\n    </InputField>\r\n\r\n    <VerticalLayout>\r\n        <GridLayout cellSize=\"190 25\"\r\n                    spacing=\"10 10\"\r\n                    rectAlignment=\"MiddleCenter\">\r\n            <Text></Text>\r\n            <Text></Text>\r\n\r\n            <Text>Deck Name</Text>\r\n            <Text id=\"deckNameText\" />\r\n\r\n            <Text>Deck Image URL</Text>\r\n            <Text></Text>\r\n\r\n            <Text>Deck Sleeves URL</Text>\r\n            <Text></Text>\r\n        </GridLayout>\r\n        <Button id=\"generateButton\" onClick=\"generateDeckViaUI\">Generate</Button>\r\n    </VerticalLayout>\r\n</Panel>",
        "CustomUIAssets": null,
        "LuaScript": "-- Deck Generator Tool v0.0.1\r\n-- This script was inspired by Card Naming Tool which was created by dzikakulka, \r\n-- and co-authored and published by Hiram Abiff.\r\n-- Created specifically for wstools, do not edit unless you know what you're doing.\r\n\r\ndeckName = \"5toubun bar/choice\"\r\nserialsJSON = \